{"sceneObjects": [{"position": {"width": 187, "top": 28, "height": 145, "left": 92}, "inText": true, "label": "toad"}, {"position": {"width": 179, "top": 91, "height": 68, "left": 69}, "inText": false, "label": "bar of soap"}, {"position": {"width": 231, "top": 18, "height": 170, "left": 57}, "inText": true, "label": "toad"}, {"position": {"width": 165, "top": 48, "height": 58, "left": 90}, "inText": true, "label": "ate"}, {"position": {"width": 174, "top": 79, "height": 88, "left": 83}, "inText": false, "label": "soap"}, {"position": {"width": 208, "top": 32, "height": 141, "left": 74}, "inText": true, "label": "toad"}], "triggers": [{"args": {"textId": 2, "timestamp": null, "sceneObjectLabel": "toad"}, "type": 0}, {"args": {"textId": 2, "timestamp": null, "sceneObjectLabel": "toad"}, "type": 0}, {"args": {"textId": 3, "timestamp": null, "sceneObjectLabel": "ate"}, "type": 0}, {"args": {"textId": 2, "timestamp": null, "sceneObjectLabel": "toad"}, "type": 0}], "text": "One day Toad ate and ate, but he was still hungry. Then he saw a bar of soap. Gulp! It got stuck in his throat.", "storyImageFile": "the_hungry_toad_05", "audioFile": "the_hungry_toad_4", "timestamps": [{"start": "0.0", "wordIdx": "0", "end": "0.3"}, {"start": "0.3", "wordIdx": "1", "end": "0.6"}, {"start": "0.6", "wordIdx": "2", "end": "1.5"}, {"start": "1.5", "wordIdx": "3", "end": "1.9"}, {"start": "1.9", "wordIdx": "4", "end": "2.5"}, {"start": "2.5", "wordIdx": "5", "end": "2.9"}, {"start": "2.9", "wordIdx": "6", "end": "3.5"}, {"start": "3.5", "wordIdx": "7", "end": "3.7"}, {"start": "3.7", "wordIdx": "8", "end": "4.0"}, {"start": "4.0", "wordIdx": "9", "end": "4.2"}, {"start": "4.2", "wordIdx": "10", "end": "4.7"}, {"start": "4.7", "wordIdx": "11", "end": "6.0"}, {"start": "6.0", "wordIdx": "12", "end": "6.2"}, {"start": "6.2", "wordIdx": "13", "end": "6.4"}, {"start": "6.4", "wordIdx": "14", "end": "6.7"}, {"start": "6.7", "wordIdx": "15", "end": "7.1"}, {"start": "7.1", "wordIdx": "16", "end": "7.3"}, {"start": "7.3", "wordIdx": "17", "end": "7.4"}, {"start": "7.4", "wordIdx": "18", "end": "8.9"}, {"start": "8.9", "wordIdx": "19", "end": "9.9"}, {"start": "9.9", "wordIdx": "20", "end": "10.3"}, {"start": "10.3", "wordIdx": "21", "end": "10.6"}, {"start": "10.6", "wordIdx": "22", "end": "10.9"}, {"start": "10.9", "wordIdx": "23", "end": "11.3"}, {"start": "11.3", "wordIdx": "24", "end": "11.5"}], "isTitle": false}